odoo/addons/web_tree_column_keyboard_resize/README.rst
odoo/addons/web_tree_column_keyboard_resize/__init__.py
odoo/addons/web_tree_column_keyboard_resize/__manifest__.py
odoo/addons/web_tree_column_keyboard_resize/i18n/it.po
odoo/addons/web_tree_column_keyboard_resize/i18n/web_tree_column_keyboard_resize.pot
odoo/addons/web_tree_column_keyboard_resize/readme/CONTRIBUTORS.md
odoo/addons/web_tree_column_keyboard_resize/readme/DESCRIPTION.md
odoo/addons/web_tree_column_keyboard_resize/static/description/icon.png
odoo/addons/web_tree_column_keyboard_resize/static/description/index.html
odoo/addons/web_tree_column_keyboard_resize/static/src/js/list_renderer.esm.js
odoo_addon_web_tree_column_keyboard_resize-18.0.1.0.0.3.dist-info/METADATA
odoo_addon_web_tree_column_keyboard_resize-18.0.1.0.0.3.dist-info/WHEEL
odoo_addon_web_tree_column_keyboard_resize-18.0.1.0.0.3.dist-info/top_level.txt
odoo_addon_web_tree_column_keyboard_resize-18.0.1.0.0.3.dist-info/RECORD
